accmtcli/__init__.py
accmtcli/accmt.py
accmtcli/launch.py
accmtcli/parser.py
accmtcli/utils.py
accmtcli/config/ddp-bf16.yaml
accmtcli/config/ddp-fp16.yaml
accmtcli/config/ddp-fp32.yaml
accmtcli/config/ddp-fp8.yaml
accmtcli/config/ddp.yaml
accmtcli/config/deepspeed-0-bf16.yaml
accmtcli/config/deepspeed-0-fp16.yaml
accmtcli/config/deepspeed-0-fp32.yaml
accmtcli/config/deepspeed-0-fp8.yaml
accmtcli/config/deepspeed-0.yaml
accmtcli/config/deepspeed-1-bf16.yaml
accmtcli/config/deepspeed-1-fp16.yaml
accmtcli/config/deepspeed-1-fp32.yaml
accmtcli/config/deepspeed-1-fp8.yaml
accmtcli/config/deepspeed-1.yaml
accmtcli/config/deepspeed-2-bf16-cpu-cpu.yaml
accmtcli/config/deepspeed-2-bf16-cpu-none.yaml
accmtcli/config/deepspeed-2-bf16-cpu-nvme.yaml
accmtcli/config/deepspeed-2-bf16-none-cpu.yaml
accmtcli/config/deepspeed-2-bf16-none-none.yaml
accmtcli/config/deepspeed-2-bf16-none-nvme.yaml
accmtcli/config/deepspeed-2-bf16-nvme-cpu.yaml
accmtcli/config/deepspeed-2-bf16-nvme-none.yaml
accmtcli/config/deepspeed-2-bf16-nvme-nvme.yaml
accmtcli/config/deepspeed-2-bf16.yaml
accmtcli/config/deepspeed-2-fp16-cpu-cpu.yaml
accmtcli/config/deepspeed-2-fp16-cpu-none.yaml
accmtcli/config/deepspeed-2-fp16-cpu-nvme.yaml
accmtcli/config/deepspeed-2-fp16-none-cpu.yaml
accmtcli/config/deepspeed-2-fp16-none-none.yaml
accmtcli/config/deepspeed-2-fp16-none-nvme.yaml
accmtcli/config/deepspeed-2-fp16-nvme-cpu.yaml
accmtcli/config/deepspeed-2-fp16-nvme-none.yaml
accmtcli/config/deepspeed-2-fp16-nvme-nvme.yaml
accmtcli/config/deepspeed-2-fp16.yaml
accmtcli/config/deepspeed-2-fp32-cpu-cpu.yaml
accmtcli/config/deepspeed-2-fp32-cpu-none.yaml
accmtcli/config/deepspeed-2-fp32-cpu-nvme.yaml
accmtcli/config/deepspeed-2-fp32-none-cpu.yaml
accmtcli/config/deepspeed-2-fp32-none-none.yaml
accmtcli/config/deepspeed-2-fp32-none-nvme.yaml
accmtcli/config/deepspeed-2-fp32-nvme-cpu.yaml
accmtcli/config/deepspeed-2-fp32-nvme-none.yaml
accmtcli/config/deepspeed-2-fp32-nvme-nvme.yaml
accmtcli/config/deepspeed-2-fp32.yaml
accmt_cli-1.4.7.1.dist-info/METADATA
accmt_cli-1.4.7.1.dist-info/WHEEL
accmt_cli-1.4.7.1.dist-info/entry_points.txt
accmt_cli-1.4.7.1.dist-info/top_level.txt
accmt_cli-1.4.7.1.dist-info/RECORD
