Metadata-Version: 2.4
Name: accmt-cli
Version: 1.4.7.1
Summary: CLI for AcceleratorModule library (accmt).
Home-page: https://github.com/ghanvert/accmt-cli
Author: ghanvert
Author-email: martin.pizarro@cenia.cl
Project-URL: Bug Tracker, https://github.com/ghanvert/accmt-cli/issues
Classifier: Programming Language :: Python :: 3
Classifier: License :: OSI Approved :: Apache Software License
Classifier: Operating System :: OS Independent
Requires-Python: >=3.10
Requires-Dist: accelerate
Requires-Dist: PyYAML
